tests/__init__.py
tests/tests_core.py
vixhal/__init__.py
vixhal/core.py
vixhal-0.0.4.dist-info/LICENSE
vixhal-0.0.4.dist-info/METADATA
vixhal-0.0.4.dist-info/WHEEL
vixhal-0.0.4.dist-info/top_level.txt
vixhal-0.0.4.dist-info/RECORD
