Metadata-Version: 2.1
Name: vixhal
Version: 0.0.4
Summary: A library designed for secure key-value storage using AES encryption. It provides functionality for generating AES keys, encrypting and decrypting data, and converting between text and bytes. The library is designed for in-memory storage, making it suitable for fast, temporary data handling.
Home-page: https://github.com/TheVixhal/vixhal
Author: Vishal Singh Baraiya
Author-email: <thevishal010@gmail.com>
Keywords: python,vixhal,encrypt,decrypt,bytes,AES,store,retrieve,generate key,secure
Classifier: Intended Audience :: Developers
Classifier: Programming Language :: Python :: 3
Classifier: License :: OSI Approved :: MIT License
Classifier: Operating System :: OS Independent
License-File: LICENSE
Requires-Dist: pycryptodome
